sinapsis_deepseek_ocr/src/sinapsis_deepseek_ocr/__init__.py
sinapsis_deepseek_ocr/src/sinapsis_deepseek_ocr/helpers/__init__.py
sinapsis_deepseek_ocr/src/sinapsis_deepseek_ocr/helpers/bbox_utils.py
sinapsis_deepseek_ocr/src/sinapsis_deepseek_ocr/helpers/grounding_parser.py
sinapsis_deepseek_ocr/src/sinapsis_deepseek_ocr/helpers/mode_registry.py
sinapsis_deepseek_ocr/src/sinapsis_deepseek_ocr/helpers/schemas.py
sinapsis_deepseek_ocr/src/sinapsis_deepseek_ocr/helpers/tags.py
sinapsis_deepseek_ocr/src/sinapsis_deepseek_ocr/templates/__init__.py
sinapsis_deepseek_ocr/src/sinapsis_deepseek_ocr/templates/deepseek_ocr_inference.py
sinapsis_doctr/src/sinapsis_doctr/__init__.py
sinapsis_doctr/src/sinapsis_doctr/helpers/__init__.py
sinapsis_doctr/src/sinapsis_doctr/helpers/tags.py
sinapsis_doctr/src/sinapsis_doctr/templates/__init__.py
sinapsis_doctr/src/sinapsis_doctr/templates/doc_tr_ocr_prediction.py
sinapsis_easyocr/src/sinapsis_easyocr/__init__.py
sinapsis_easyocr/src/sinapsis_easyocr/helpers/__init__.py
sinapsis_easyocr/src/sinapsis_easyocr/helpers/tags.py
sinapsis_easyocr/src/sinapsis_easyocr/templates/__init__.py
sinapsis_easyocr/src/sinapsis_easyocr/templates/easy_ocr.py
sinapsis_ocr-0.2.0.dist-info/licenses/LICENSE
sinapsis_ocr-0.2.0.dist-info/METADATA
sinapsis_ocr-0.2.0.dist-info/WHEEL
sinapsis_ocr-0.2.0.dist-info/top_level.txt
sinapsis_ocr-0.2.0.dist-info/RECORD
