Metadata-Version: 2.4
Name: sinapsis-ocr
Version: 0.2.0
Summary: Implements Sinapsis templates to perform optical character recognition on images
Author-email: SinapsisAI <dev@sinapsis.tech>
Project-URL: Homepage, https://sinapsis.tech
Project-URL: Documentation, https://docs.sinapsis.tech/docs
Project-URL: Tutorials, https://docs.sinapsis.tech/tutorials
Project-URL: Repository, https://github.com/Sinapsis-AI/sinapsis-ocr.git
Requires-Python: >=3.10
License-File: LICENSE
Requires-Dist: sinapsis>=0.1.1
Provides-Extra: webapp-gradio
Requires-Dist: sinapsis-data-visualization[visualization-matplotlib]>=0.1.0; extra == "webapp-gradio"
Requires-Dist: sinapsis[webapp]>=0.2.7; extra == "webapp-gradio"
Provides-Extra: all
Requires-Dist: sinapsis-ocr[webapp-gradio]; extra == "all"
Requires-Dist: sinapsis-doctr[all]; extra == "all"
Requires-Dist: sinapsis-easyocr[all]; extra == "all"
Requires-Dist: sinapsis-deepseek-ocr[all]; extra == "all"
Dynamic: license-file
